bschlorinator/__init__.py
bschlorinator/chlorinator.py
bschlorinator/const.py
bschlorinator-0.4.2.dist-info/METADATA
bschlorinator-0.4.2.dist-info/WHEEL
bschlorinator-0.4.2.dist-info/RECORD
