Metadata-Version: 2.3
Name: bschlorinator
Version: 0.4.2
Summary: Package to send and recieve data from bs pools chlorinator unit and controlling ralays(On, off, programm time).
License: MIT
Author: Vaclav Silhan
Author-email: Katamave@gmail.com
Requires-Python: >=3.11
Classifier: License :: OSI Approved :: MIT License
Classifier: Programming Language :: Python :: 3
Classifier: Programming Language :: Python :: 3.11
Classifier: Programming Language :: Python :: 3.12
Classifier: Programming Language :: Python :: 3.13
Requires-Dist: pyserial (>=3.5,<4.0)
Requires-Dist: rpi-gpio (>=0.7.1,<0.8.0)
